govee_lan_api/__init__.py
govee_lan_api/api_requests.py
govee_lan_api/client.py
govee_lan_api/listener.py
govee_lan_api-0.2.0.dist-info/WHEEL
govee_lan_api-0.2.0.dist-info/METADATA
govee_lan_api-0.2.0.dist-info/RECORD
