Metadata-Version: 2.1
Name: govee-lan-api
Version: 0.2.0
Summary: Implementation of the Govee LAN API to control supported Govee products
License: MIT
Author: Ryan McDonough
Author-email: Ryan@r2n.io
Requires-Python: >=3.10,<4.0
Classifier: License :: OSI Approved :: MIT License
Classifier: Programming Language :: Python :: 3
Classifier: Programming Language :: Python :: 3.10
Classifier: Programming Language :: Python :: 3.11
